maildropy/__init__.py
maildropy-1.0.0.dist-info/METADATA
maildropy-1.0.0.dist-info/WHEEL
maildropy-1.0.0.dist-info/licenses/LICENSE
maildropy-1.0.0.dist-info/RECORD
