Metadata-Version: 2.3
Name: maildropy
Version: 1.0.0
Summary: A Python package to read emails from maildrop.cc
Project-URL: Homepage, https://github.com/leolivier/maildropy
Project-URL: Repository, https://github.com/leolivier/maildropy.git
Project-URL: Issues, https://github.com/leolivier/maildropy/issues
Project-URL: Download, https://github.com/leolivier/maildropy/archive/refs/tags/1.0.0.tar.gz
Author-email: Olivier LEVILLAIN <levillain.olivier@gmail.com>
License-File: LICENSE
Keywords: disposable,mail,maildrop,python,throwable
Classifier: Development Status :: 4 - Beta
Classifier: License :: OSI Approved :: MIT License
Classifier: Operating System :: OS Independent
Classifier: Programming Language :: Python :: 3
Requires-Python: >=3.10
Requires-Dist: certifi
Requires-Dist: python-dotenv
Requires-Dist: requests
Requires-Dist: urllib3
